overmind/__init__.py
overmind/_vendor/__init__.py
overmind/_vendor/opentelemetry_instrumentation_openai/__init__.py
overmind/_vendor/opentelemetry_instrumentation_openai/shared/__init__.py
overmind/_vendor/opentelemetry_instrumentation_openai/shared/chat_wrappers.py
overmind/_vendor/opentelemetry_instrumentation_openai/shared/completion_wrappers.py
overmind/_vendor/opentelemetry_instrumentation_openai/shared/config.py
overmind/_vendor/opentelemetry_instrumentation_openai/shared/embeddings_wrappers.py
overmind/_vendor/opentelemetry_instrumentation_openai/shared/event_emitter.py
overmind/_vendor/opentelemetry_instrumentation_openai/shared/event_models.py
overmind/_vendor/opentelemetry_instrumentation_openai/shared/image_gen_wrappers.py
overmind/_vendor/opentelemetry_instrumentation_openai/shared/span_utils.py
overmind/_vendor/opentelemetry_instrumentation_openai/utils.py
overmind/_vendor/opentelemetry_instrumentation_openai/v0/__init__.py
overmind/_vendor/opentelemetry_instrumentation_openai/v1/__init__.py
overmind/_vendor/opentelemetry_instrumentation_openai/v1/assistant_wrappers.py
overmind/_vendor/opentelemetry_instrumentation_openai/v1/event_handler_wrapper.py
overmind/_vendor/opentelemetry_instrumentation_openai/v1/realtime_wrappers.py
overmind/_vendor/opentelemetry_instrumentation_openai/v1/responses_wrappers.py
overmind/_vendor/opentelemetry_instrumentation_openai/version.py
overmind/agents.py
overmind/client.py
overmind/exceptions.py
overmind/langchain/__init__.py
overmind/langchain/callbacks.py
overmind/layers.py
overmind/models.py
overmind/overmind_sdk.py
overmind/policies.py
overmind/utils/__init__.py
overmind/utils/api_settings.py
overmind/utils/formatters.py
overmind/utils/serializers.py
overmind-0.1.18.dist-info/METADATA
overmind-0.1.18.dist-info/WHEEL
overmind-0.1.18.dist-info/licenses/LICENSE
overmind-0.1.18.dist-info/RECORD
