Metadata-Version: 2.4
Name: overmind
Version: 0.1.18
Summary: Python client for Overmind API
License-File: LICENSE
Keywords: overmind,ai,api,client,policy,enforcement
Author: Overmind Ltd
Requires-Python: >=3.9,<4
Classifier: Development Status :: 3 - Alpha
Classifier: Intended Audience :: Developers
Classifier: License :: OSI Approved :: MIT License
Classifier: Operating System :: OS Independent
Classifier: Programming Language :: Python :: 3
Classifier: Programming Language :: Python :: 3.9
Classifier: Programming Language :: Python :: 3.10
Classifier: Programming Language :: Python :: 3.11
Classifier: Programming Language :: Python :: 3.12
Classifier: Programming Language :: Python :: 3.13
Classifier: Programming Language :: Python :: 3.14
Classifier: Programming Language :: Python :: 3.8
Provides-Extra: full
Requires-Dist: langgraph (>=0.5.4,<0.6.0)
Requires-Dist: opentelemetry-api (>=1.35.0,<2.0.0)
Requires-Dist: opentelemetry-exporter-otlp-proto-http (>=1.35.0,<2.0.0)
Requires-Dist: opentelemetry-instrumentation (>=0.60b1)
Requires-Dist: opentelemetry-instrumentation-fastapi (>=0.60b1,<0.61)
Requires-Dist: opentelemetry-instrumentation-httpx (>=0.60b1,<0.61) ; extra == "full"
Requires-Dist: opentelemetry-instrumentation-logging (>=0.60b1,<0.61) ; extra == "full"
Requires-Dist: opentelemetry-instrumentation-requests (>=0.60b1,<0.61) ; extra == "full"
Requires-Dist: opentelemetry-sdk (>=1.35.0,<2.0.0)
Requires-Dist: opentelemetry-semantic-conventions (>=0.60b1)
Requires-Dist: opentelemetry-semantic-conventions-ai (>=0.4.13,<0.5.0)
Requires-Dist: packaging (>=23.0,<24.0)
Requires-Dist: pydantic (>=2.0.0,<3.0.0)
Requires-Dist: requests (>=2.31.0,<3.0.0)
Requires-Dist: rich (>=14.0.0,<15.0.0)
Requires-Dist: typing-extensions (>=4.0.0,<5.0.0)
Requires-Dist: wrapt (>=1.14.0,<2.0.0)
Project-URL: Homepage, https://github.com/overmind-core/overmind-python
Project-URL: Repository, https://github.com/overmind-core/overmind-python
